[
    {
        "title": "Tim Cook joins the billionaire club as Apple’s value climbs toward $2 trillion",
        "score": 6974,
        "url": "https://9to5mac.com/2020/08/10/tim-cook-net-worth/",
        "content": "",
        "created_utc": 1597084181.0,
        "subreddit_name": "apple",
        "comments": 827
    },
    {
        "title": "Apple goes to war with the gaming industry",
        "score": 5082,
        "url": "https://techcrunch.com/2020/08/09/apple-goes-to-war-with-the-gaming-industry/",
        "content": "",
        "created_utc": 1597050799.0,
        "subreddit_name": "apple",
        "comments": 1182
    }
]