[
    {
        "title": "Why was Berkshire Hathaway So heavy invested in Apple?",
        "score": 383,
        "url": "https://www.reddit.com/r/stocks/comments/1erowrl/why_was_berkshire_hathaway_so_heavy_invested_in/",
        "content": "Last week it was announced that BH cut 50% of their stake in Apple. Before the cut the stock represented 44% of the company's whole portfolio. To me this ratio seems incredibly excessive compared to most big holding companies. I think Apple is a good stock to own. But, why would the company put so many eggs in one basket? It doesn't seem like good risk management to me?",
        "created_utc": 1723598664.0,
        "subreddit_name": "stocks",
        "comments": 179
    },
    {
        "title": "Alphabet Breakup ",
        "score": 215,
        "url": "https://www.reddit.com/r/stocks/comments/1es9s76/alphabet_breakup/",
        "content": "How do you think the Alphabet breakup proposal will go over? Do you think this is a guaranteed thing, or do you think it will get shot down in appeals? Do you believe this will trickle down into other companies like MSFT, Apple etc? Any opinions are appreciated, thanks ",
        "created_utc": 1723661844.0,
        "subreddit_name": "stocks",
        "comments": 150
    }
]