[
    {
        "title": "iPhone 17 'Slim': Everything We Know So Far",
        "score": 1144,
        "url": "https://www.macrumors.com/2024/07/05/iphone-17-slim-everything-we-know/",
        "content": "",
        "created_utc": 1720182996.0,
        "subreddit_name": "apple",
        "comments": 459
    },
    {
        "title": "Apple M5 Chip's Dual-Use Design Will Power Future Macs and AI Servers",
        "score": 6,
        "url": "https://www.macrumors.com/2024/07/04/apple-m5-chips-advanced-packaging-tsmc/",
        "content": "",
        "created_utc": 1720175878.0,
        "subreddit_name": "AAPL",
        "comments": 1
    },
    {
        "title": "New AAPL options position",
        "score": 2,
        "url": "https://www.reddit.com/gallery/1dvz007",
        "content": "Apple AAPL hitting new ATHs",
        "created_utc": 1720188874.0,
        "subreddit_name": "AAPL",
        "comments": 7
    },
    {
        "title": "Leak Confirms Apple's Work On 'Home Accessory'",
        "score": 1,
        "url": "https://www.macrumors.com/2024/07/04/leak-confirms-apples-work-on-home-accessory/",
        "content": "",
        "created_utc": 1720146416.0,
        "subreddit_name": "AAPL",
        "comments": 0
    }
]