[
    {
        "title": "Tesla passes Facebook to become fifth most valuable U.S. company",
        "score": 5149,
        "url": "https://www.reddit.com/r/stocks/comments/kt4dsy/tesla_passes_facebook_to_become_fifth_most/",
        "content": "https://www.cnbc.com/2021/01/07/tesla-passes-facebook-to-become-fifth-most-valuable-us-company.html\n\nTesla has surpassed Facebook by market cap.\n\nThe jump makes it the fifth biggest company in the large-cap benchmark when counting the share classes of Alphabet together.\n\nIt now just trails Apple, Microsoft, Amazon and Alphabet.\n\nThanks for the awards.",
        "created_utc": 1610118887.0,
        "subreddit_name": "stocks",
        "comments": 761
    },
    {
        "title": "Woman who falsely said Black teen stole her phone in NYC hotel arrested in home state of California",
        "score": 75787,
        "url": "https://www.cbsnews.com/news/soho-karen-arrested-miya-ponsetto-falsely-said-black-teen-stole-her-phone-nyc-hotel/",
        "content": "",
        "created_utc": 1610103856.0,
        "subreddit_name": "news",
        "comments": 3608
    },
    {
        "title": "Apple says it will kick Parler off the App Store in 24 hours unless content is moderated",
        "score": 30441,
        "url": "https://9to5mac.com/2021/01/08/apple-says-it-will-kick-parler-off-the-app-store-in-24-hours-unless-content-is-moderated/",
        "content": "",
        "created_utc": 1610147621.0,
        "subreddit_name": "apple",
        "comments": 4146
    }
]